pyhanoi/__init__.py
pyhanoi/__main__.py
pyhanoi/libhanoi.py
pyhanoi/libhanoi_test.py
pyhanoi_pt-0.2.dist-info/METADATA
pyhanoi_pt-0.2.dist-info/WHEEL
pyhanoi_pt-0.2.dist-info/licenses/LICENSE.txt
pyhanoi_pt-0.2.dist-info/RECORD
