Metadata-Version: 2.1
Name: PyHanoi_PT
Version: 0.2
Summary: A universal brute-force tower of hanoi solver
Project-URL: Homepage, https://github.com/pranavtaysheti/PyHanoi
Author-email: Pranav Taysheti <pranavtaysheti@gmail.com>
License-File: LICENSE.txt
Classifier: License :: OSI Approved :: GNU General Public License v3 or later (GPLv3+)
Classifier: Operating System :: OS Independent
Classifier: Programming Language :: Python :: 3.10
